Metadata-Version: 2.1
Name: materialsmap
Version: 0.2.2
Summary: MaterialsMap is Python package for mapping properties, manufacturing feasibility, and desirability. We focus on guiding materials design graphically while proving API to underlying methods.
Author-email: Hui Sun <HuiSun@psu.edu>
Project-URL: Homepage, https://github.com/HUISUN24/materialsmap
Project-URL: Research Group, https://phaseslab.org
Project-URL: Bug Tracker, https://github.com/HUISUN24/materialsmap/issues
Classifier: Programming Language :: Python :: 3
Classifier: Programming Language :: Python :: 3.8
Classifier: Programming Language :: Python :: 3.9
Classifier: Development Status :: 3 - Alpha
Classifier: Intended Audience :: Science/Research
Classifier: License :: OSI Approved :: MIT License
Classifier: Operating System :: OS Independent
Classifier: Topic :: Scientific/Engineering
Classifier: Topic :: Scientific/Engineering :: Chemistry
Classifier: Topic :: Scientific/Engineering :: Physics
Requires-Python: <3.10,>=3.8
License-File: LICENSE
Requires-Dist: matplotlib <3.8
Requires-Dist: numpy <=1.22
Requires-Dist: pycalphad <=0.9.2
Requires-Dist: pandas >=2.0.2
Requires-Dist: tqdm >=4.65.0
Requires-Dist: scheil >=0.1.6
Requires-Dist: scikit-learn >=0.24.1
Requires-Dist: openpyxl >=3.1.2
